{
  "template": "",
  "ruleGroups": [],
  "entityClass": "com.adjecti.pis.liferay.model.IDAMFailedTransaction",
  "formClass": "IDAMFailedTransactionForm",
  "columns": 1,
  "selectable": true,
  "formFlowProcess": false,
  "caption": true,
  "addNew": false,
  "relationEntities": {},
  "title": "I D A M Failed Transaction",
  "autoLabelElements": true,
  "elementsPerRow": 1,
  "accessType": "field",
  "crud": true,
  "encType": "application/x-www-form-urlencoded",
  "tab": false,
  "id": "IdamFailedTransactionForm_123456",
  "tabTitles": [],
  "advanceFilter": true,
  "elementNamespace": "",
  "formType": "basic",
  "allElements": [
    {
      "listOptions": [],
      "ruleGroups": [],
      "validType": "none",
      "dayBefore": "",
      "defaultValue": "",
      "minLength": 0,
      "tooltip": false,
      "elementsPerColumn": 0,
      "rules": [],
      "formFlowKey": false,
      "required": false,
      "relation": null,
      "monthBefore": "",
      "tab": false,
      "dateBefore": "",
      "folderAutoCreate": false,
      "exclude": false,
      "events": [],
      "placeHolder": "",
      "group": 0,
      "height": 0,
      "thumbnail": false,
      "depends": "",
      "dataType": "",
      "yearAfter": "",
      "format": "",
      "readOnly": "",
      "dataQuery": "",
      "customTemplate": "",
      "regExp": "",
      "accept": "",
      "matchWith": "",
      "dateAfter": "",
      "folder": "0",
      "fileSize": "0",
      "unique": false,
      "mappingField": "",
      "name": "idamFailedTransactionId",
      "tableRowAlign": "horizontal",
      "maxLength": 75,
      "preview": false,
      "listable": true,
      "formClass": "Object",
      "hidden": true,
      "link": false,
      "childForm": null,
      "linkAction": "",
      "dayAfter": "",
      "min": 0,
      "transientElement": false,
      "listField": "",
      "attribute": "idamFailedTransactionId",
      "cols": 0,
      "value": "",
      "dependantKey": "",
      "key": true,
      "helpText": "",
      "max": 0,
      "seachable": false,
      "parentForm": null,
      "label": "Idam Failed Transaction",
      "rows": 0,
      "yearBefore": "",
      "controlType": "hidden",
      "displayWidth": "",
      "width": 0,
      "monthAfter": ""
    },
    {
      "listOptions": [],
      "ruleGroups": [],
      "validType": "none",
      "dayBefore": "",
      "defaultValue": "",
      "minLength": 0,
      "tooltip": false,
      "elementsPerColumn": 0,
      "rules": [],
      "formFlowKey": false,
      "required": false,
      "relation": {
        "filter": {},
        "mappingClass": "java.lang.Object",
        "modelClass": "com.adjecti.pis.liferay.model.Employee",
        "mappingField": "",
        "type": "None",
        "valueField": "employeeId",
        "lazyLoad": true,
        "labelField": "fullName_En"
      },
      "monthBefore": "",
      "tab": false,
      "dateBefore": "",
      "folderAutoCreate": false,
      "exclude": false,
      "events": [],
      "placeHolder": "",
      "group": 0,
      "height": 0,
      "thumbnail": false,
      "depends": "",
      "dataType": "",
      "yearAfter": "",
      "format": "",
      "readOnly": "",
      "dataQuery": "",
      "customTemplate": "",
      "regExp": "",
      "accept": "",
      "matchWith": "",
      "dateAfter": "",
      "folder": "0",
      "fileSize": "0",
      "unique": false,
      "mappingField": "",
      "name": "employeeId",
      "tableRowAlign": "horizontal",
      "maxLength": 75,
      "preview": false,
      "listable": true,
      "formClass": "Object",
      "hidden": false,
      "link": false,
      "childForm": null,
      "linkAction": "",
      "dayAfter": "",
      "min": 0,
      "transientElement": false,
      "listField": "name",
      "attribute": "employeeId",
      "cols": 0,
      "value": "",
      "dependantKey": "",
      "key": false,
      "helpText": "",
      "max": 0,
      "seachable": false,
      "parentForm": null,
      "label": "Employee Name",
      "rows": 0,
      "yearBefore": "",
      "controlType": "select",
      "displayWidth": "",
      "width": 0,
      "monthAfter": ""
    },
    {
      "listOptions": [],
      "ruleGroups": [],
      "validType": "none",
      "dayBefore": "",
      "defaultValue": "",
      "minLength": 0,
      "tooltip": false,
      "elementsPerColumn": 0,
      "rules": [],
      "formFlowKey": false,
      "required": false,
      "relation": null,
      "monthBefore": "",
      "tab": false,
      "dateBefore": "",
      "folderAutoCreate": false,
      "exclude": false,
      "events": [],
      "placeHolder": "",
      "group": 0,
      "height": 0,
      "thumbnail": false,
      "depends": "",
      "dataType": "",
      "yearAfter": "",
      "format": "",
      "readOnly": "",
      "dataQuery": "",
      "customTemplate": "",
      "regExp": "",
      "accept": "",
      "matchWith": "",
      "dateAfter": "",
      "folder": "0",
      "fileSize": "0",
      "unique": false,
      "mappingField": "",
      "name": "idamUrl",
      "tableRowAlign": "horizontal",
      "maxLength": 75,
      "preview": false,
      "listable": true,
      "formClass": "Object",
      "hidden": false,
      "link": false,
      "childForm": null,
      "linkAction": "",
      "dayAfter": "",
      "min": 0,
      "transientElement": false,
      "listField": "",
      "attribute": "idamUrl",
      "cols": 0,
      "value": "",
      "dependantKey": "",
      "key": false,
      "helpText": "",
      "max": 0,
      "seachable": false,
      "parentForm": null,
      "label": "Idam Url",
      "rows": 0,
      "yearBefore": "",
      "controlType": "text",
      "displayWidth": "",
      "width": 0,
      "monthAfter": ""
    },
    {
      "listOptions": [],
      "ruleGroups": [],
      "validType": "none",
      "dayBefore": "",
      "defaultValue": "",
      "minLength": 0,
      "tooltip": false,
      "elementsPerColumn": 0,
      "rules": [],
      "formFlowKey": false,
      "required": false,
      "relation": null,
      "monthBefore": "",
      "tab": false,
      "dateBefore": "",
      "folderAutoCreate": false,
      "exclude": false,
      "events": [],
      "placeHolder": "",
      "group": 0,
      "height": 0,
      "thumbnail": false,
      "depends": "",
      "dataType": "",
      "yearAfter": "",
      "format": "",
      "readOnly": "",
      "dataQuery": "",
      "customTemplate": "",
      "regExp": "",
      "accept": "",
      "matchWith": "",
      "dateAfter": "",
      "folder": "0",
      "fileSize": "0",
      "unique": false,
      "mappingField": "",
      "name": "className",
      "tableRowAlign": "horizontal",
      "maxLength": 75,
      "preview": false,
      "listable": true,
      "formClass": "Object",
      "hidden": false,
      "link": false,
      "childForm": null,
      "linkAction": "",
      "dayAfter": "",
      "min": 0,
      "transientElement": false,
      "listField": "",
      "attribute": "className",
      "cols": 0,
      "value": "",
      "dependantKey": "",
      "key": false,
      "helpText": "",
      "max": 0,
      "seachable": false,
      "parentForm": null,
      "label": "Class Name",
      "rows": 0,
      "yearBefore": "",
      "controlType": "text",
      "displayWidth": "",
      "width": 0,
      "monthAfter": ""
    },
    {
      "listOptions": [],
      "ruleGroups": [],
      "validType": "none",
      "dayBefore": "",
      "defaultValue": "",
      "minLength": 0,
      "tooltip": true,
      "elementsPerColumn": 0,
      "rules": [],
      "formFlowKey": false,
      "required": false,
      "relation": null,
      "monthBefore": "",
      "tab": false,
      "dateBefore": "",
      "folderAutoCreate": false,
      "exclude": false,
      "events": [],
      "placeHolder": "",
      "group": 0,
      "height": 0,
      "thumbnail": false,
      "depends": "",
      "dataType": "",
      "yearAfter": "",
      "format": "",
      "readOnly": "",
      "dataQuery": "",
      "customTemplate": "",
      "regExp": "",
      "accept": "",
      "matchWith": "",
      "dateAfter": "",
      "folder": "0",
      "fileSize": "0",
      "unique": false,
      "mappingField": "",
      "name": "attribute",
      "tableRowAlign": "horizontal",
      "maxLength": 75,
      "preview": false,
      "listable": true,
      "formClass": "Object",
      "hidden": false,
      "link": false,
      "childForm": null,
      "linkAction": "",
      "dayAfter": "",
      "min": 0,
      "transientElement": false,
      "listField": "",
      "attribute": "attribute",
      "cols": 0,
      "value": "",
      "dependantKey": "",
      "key": false,
      "helpText": "",
      "max": 0,
      "seachable": false,
      "parentForm": null,
      "label": "Attribute",
      "rows": 0,
      "yearBefore": "",
      "controlType": "text",
      "displayWidth": "",
      "width": 0,
      "monthAfter": ""
    },
    {
      "listOptions": [],
      "ruleGroups": [],
      "validType": "none",
      "dayBefore": "",
      "defaultValue": "",
      "minLength": 0,
      "tooltip": true,
      "elementsPerColumn": 0,
      "rules": [],
      "formFlowKey": false,
      "required": false,
      "relation": null,
      "monthBefore": "",
      "tab": false,
      "dateBefore": "",
      "folderAutoCreate": false,
      "exclude": false,
      "events": [],
      "placeHolder": "",
      "group": 0,
      "height": 0,
      "thumbnail": false,
      "depends": "",
      "dataType": "",
      "yearAfter": "",
      "format": "",
      "readOnly": "",
      "dataQuery": "",
      "customTemplate": "",
      "regExp": "",
      "accept": "",
      "matchWith": "",
      "dateAfter": "",
      "folder": "0",
      "fileSize": "0",
      "unique": false,
      "mappingField": "",
      "name": "oldValue",
      "tableRowAlign": "horizontal",
      "maxLength": 75,
      "preview": false,
      "listable": true,
      "formClass": "Object",
      "hidden": false,
      "link": false,
      "childForm": null,
      "linkAction": "",
      "dayAfter": "",
      "min": 0,
      "transientElement": false,
      "listField": "",
      "attribute": "oldValue",
      "cols": 0,
      "value": "",
      "dependantKey": "",
      "key": false,
      "helpText": "",
      "max": 0,
      "seachable": false,
      "parentForm": null,
      "label": "Old Value",
      "rows": 0,
      "yearBefore": "",
      "controlType": "text",
      "displayWidth": "",
      "width": 0,
      "monthAfter": ""
    },
    {
      "listOptions": [],
      "ruleGroups": [],
      "validType": "none",
      "dayBefore": "",
      "defaultValue": "",
      "minLength": 0,
      "tooltip": true,
      "elementsPerColumn": 0,
      "rules": [],
      "formFlowKey": false,
      "required": false,
      "relation": null,
      "monthBefore": "",
      "tab": false,
      "dateBefore": "",
      "folderAutoCreate": false,
      "exclude": false,
      "events": [],
      "placeHolder": "",
      "group": 0,
      "height": 0,
      "thumbnail": false,
      "depends": "",
      "dataType": "",
      "yearAfter": "",
      "format": "",
      "readOnly": "",
      "dataQuery": "",
      "customTemplate": "",
      "regExp": "",
      "accept": "",
      "matchWith": "",
      "dateAfter": "",
      "folder": "0",
      "fileSize": "0",
      "unique": false,
      "mappingField": "",
      "name": "newValue",
      "tableRowAlign": "horizontal",
      "maxLength": 75,
      "preview": false,
      "listable": true,
      "formClass": "Object",
      "hidden": false,
      "link": false,
      "childForm": null,
      "linkAction": "",
      "dayAfter": "",
      "min": 0,
      "transientElement": false,
      "listField": "",
      "attribute": "newValue",
      "cols": 0,
      "value": "",
      "dependantKey": "",
      "key": false,
      "helpText": "",
      "max": 0,
      "seachable": false,
      "parentForm": null,
      "label": "New Value",
      "rows": 0,
      "yearBefore": "",
      "controlType": "text",
      "displayWidth": "",
      "width": 0,
      "monthAfter": ""
    },
    {
      "listOptions": [],
      "ruleGroups": [],
      "validType": "none",
      "dayBefore": "",
      "defaultValue": "",
      "minLength": 0,
      "tooltip": false,
      "elementsPerColumn": 0,
      "rules": [],
      "formFlowKey": false,
      "required": false,
      "relation": null,
      "monthBefore": "",
      "tab": false,
      "dateBefore": "",
      "folderAutoCreate": false,
      "exclude": false,
      "events": [],
      "placeHolder": "",
      "group": 0,
      "height": 0,
      "thumbnail": false,
      "depends": "",
      "dataType": "",
      "yearAfter": "",
      "format": "",
      "readOnly": "",
      "dataQuery": "",
      "customTemplate": "",
      "regExp": "",
      "accept": "",
      "matchWith": "",
      "dateAfter": "",
      "folder": "0",
      "fileSize": "0",
      "unique": false,
      "mappingField": "",
      "name": "firedon",
      "tableRowAlign": "horizontal",
      "maxLength": 75,
      "preview": false,
      "listable": true,
      "formClass": "Object",
      "hidden": false,
      "link": false,
      "childForm": null,
      "linkAction": "",
      "dayAfter": "",
      "min": 0,
      "transientElement": false,
      "listField": "",
      "attribute": "firedon",
      "cols": 0,
      "value": "",
      "dependantKey": "",
      "key": false,
      "helpText": "",
      "max": 0,
      "seachable": true,
      "parentForm": null,
      "label": "Firedon",
      "rows": 0,
      "yearBefore": "",
      "controlType": "text",
      "displayWidth": "",
      "width": 0,
      "monthAfter": ""
    }
  ],
  "formFlow": false,
  "elementGroups": [],
  "tabLayout": "horizontal",
  "readOnly": false,
  "childTabCount": 0,
  "filter": {},
  "groupAlignment": "vertical",
  "associationManyKey": "",
  "elements": [
    {
      "listOptions": [],
      "ruleGroups": [],
      "validType": "none",
      "dayBefore": "",
      "defaultValue": "",
      "minLength": 0,
      "tooltip": false,
      "elementsPerColumn": 0,
      "rules": [],
      "formFlowKey": false,
      "required": false,
      "relation": null,
      "monthBefore": "",
      "tab": false,
      "dateBefore": "",
      "folderAutoCreate": false,
      "exclude": false,
      "events": [],
      "placeHolder": "",
      "group": 0,
      "height": 0,
      "thumbnail": false,
      "depends": "",
      "dataType": "",
      "yearAfter": "",
      "format": "",
      "readOnly": "",
      "dataQuery": "",
      "customTemplate": "",
      "regExp": "",
      "accept": "",
      "matchWith": "",
      "dateAfter": "",
      "folder": "0",
      "fileSize": "0",
      "unique": false,
      "mappingField": "",
      "name": "idamFailedTransactionId",
      "tableRowAlign": "horizontal",
      "maxLength": 75,
      "preview": false,
      "listable": true,
      "formClass": "Object",
      "hidden": true,
      "link": false,
      "childForm": null,
      "linkAction": "",
      "dayAfter": "",
      "min": 0,
      "transientElement": false,
      "listField": "",
      "attribute": "idamFailedTransactionId",
      "cols": 0,
      "value": "",
      "dependantKey": "",
      "key": true,
      "helpText": "",
      "max": 0,
      "seachable": false,
      "parentForm": null,
      "label": "Idam Failed Transaction",
      "rows": 0,
      "yearBefore": "",
      "controlType": "hidden",
      "displayWidth": "",
      "width": 0,
      "monthAfter": ""
    },
    {
      "listOptions": [],
      "ruleGroups": [],
      "validType": "none",
      "dayBefore": "",
      "defaultValue": "",
      "minLength": 0,
      "tooltip": false,
      "elementsPerColumn": 0,
      "rules": [],
      "formFlowKey": false,
      "required": false,
      "relation": {
        "filter": {},
        "mappingClass": "java.lang.Object",
        "modelClass": "com.adjecti.pis.liferay.model.Employee",
        "mappingField": "",
        "type": "None",
        "valueField": "employeeId",
        "lazyLoad": true,
        "labelField": "fullName_En"
      },
      "monthBefore": "",
      "tab": false,
      "dateBefore": "",
      "folderAutoCreate": false,
      "exclude": false,
      "events": [],
      "placeHolder": "",
      "group": 0,
      "height": 0,
      "thumbnail": false,
      "depends": "",
      "dataType": "",
      "yearAfter": "",
      "format": "",
      "readOnly": "",
      "dataQuery": "",
      "customTemplate": "",
      "regExp": "",
      "accept": "",
      "matchWith": "",
      "dateAfter": "",
      "folder": "0",
      "fileSize": "0",
      "unique": false,
      "mappingField": "",
      "name": "employeeId",
      "tableRowAlign": "horizontal",
      "maxLength": 75,
      "preview": false,
      "listable": true,
      "formClass": "Object",
      "hidden": false,
      "link": false,
      "childForm": null,
      "linkAction": "",
      "dayAfter": "",
      "min": 0,
      "transientElement": false,
      "listField": "name",
      "attribute": "employeeId",
      "cols": 0,
      "value": "",
      "dependantKey": "",
      "key": false,
      "helpText": "",
      "max": 0,
      "seachable": false,
      "parentForm": null,
      "label": "Employee Name",
      "rows": 0,
      "yearBefore": "",
      "controlType": "select",
      "displayWidth": "",
      "width": 0,
      "monthAfter": ""
    },
    {
      "listOptions": [],
      "ruleGroups": [],
      "validType": "none",
      "dayBefore": "",
      "defaultValue": "",
      "minLength": 0,
      "tooltip": false,
      "elementsPerColumn": 0,
      "rules": [],
      "formFlowKey": false,
      "required": false,
      "relation": null,
      "monthBefore": "",
      "tab": false,
      "dateBefore": "",
      "folderAutoCreate": false,
      "exclude": false,
      "events": [],
      "placeHolder": "",
      "group": 0,
      "height": 0,
      "thumbnail": false,
      "depends": "",
      "dataType": "",
      "yearAfter": "",
      "format": "",
      "readOnly": "",
      "dataQuery": "",
      "customTemplate": "",
      "regExp": "",
      "accept": "",
      "matchWith": "",
      "dateAfter": "",
      "folder": "0",
      "fileSize": "0",
      "unique": false,
      "mappingField": "",
      "name": "idamUrl",
      "tableRowAlign": "horizontal",
      "maxLength": 75,
      "preview": false,
      "listable": true,
      "formClass": "Object",
      "hidden": false,
      "link": false,
      "childForm": null,
      "linkAction": "",
      "dayAfter": "",
      "min": 0,
      "transientElement": false,
      "listField": "",
      "attribute": "idamUrl",
      "cols": 0,
      "value": "",
      "dependantKey": "",
      "key": false,
      "helpText": "",
      "max": 0,
      "seachable": false,
      "parentForm": null,
      "label": "Idam Url",
      "rows": 0,
      "yearBefore": "",
      "controlType": "text",
      "displayWidth": "",
      "width": 0,
      "monthAfter": ""
    },
    {
      "listOptions": [],
      "ruleGroups": [],
      "validType": "none",
      "dayBefore": "",
      "defaultValue": "",
      "minLength": 0,
      "tooltip": false,
      "elementsPerColumn": 0,
      "rules": [],
      "formFlowKey": false,
      "required": false,
      "relation": null,
      "monthBefore": "",
      "tab": false,
      "dateBefore": "",
      "folderAutoCreate": false,
      "exclude": false,
      "events": [],
      "placeHolder": "",
      "group": 0,
      "height": 0,
      "thumbnail": false,
      "depends": "",
      "dataType": "",
      "yearAfter": "",
      "format": "",
      "readOnly": "",
      "dataQuery": "",
      "customTemplate": "",
      "regExp": "",
      "accept": "",
      "matchWith": "",
      "dateAfter": "",
      "folder": "0",
      "fileSize": "0",
      "unique": false,
      "mappingField": "",
      "name": "className",
      "tableRowAlign": "horizontal",
      "maxLength": 75,
      "preview": false,
      "listable": true,
      "formClass": "Object",
      "hidden": false,
      "link": false,
      "childForm": null,
      "linkAction": "",
      "dayAfter": "",
      "min": 0,
      "transientElement": false,
      "listField": "",
      "attribute": "className",
      "cols": 0,
      "value": "",
      "dependantKey": "",
      "key": false,
      "helpText": "",
      "max": 0,
      "seachable": false,
      "parentForm": null,
      "label": "Class Name",
      "rows": 0,
      "yearBefore": "",
      "controlType": "text",
      "displayWidth": "",
      "width": 0,
      "monthAfter": ""
    },
    {
      "listOptions": [],
      "ruleGroups": [],
      "validType": "none",
      "dayBefore": "",
      "defaultValue": "",
      "minLength": 0,
      "tooltip": true,
      "elementsPerColumn": 0,
      "rules": [],
      "formFlowKey": false,
      "required": false,
      "relation": null,
      "monthBefore": "",
      "tab": false,
      "dateBefore": "",
      "folderAutoCreate": false,
      "exclude": false,
      "events": [],
      "placeHolder": "",
      "group": 0,
      "height": 0,
      "thumbnail": false,
      "depends": "",
      "dataType": "",
      "yearAfter": "",
      "format": "",
      "readOnly": "",
      "dataQuery": "",
      "customTemplate": "",
      "regExp": "",
      "accept": "",
      "matchWith": "",
      "dateAfter": "",
      "folder": "0",
      "fileSize": "0",
      "unique": false,
      "mappingField": "",
      "name": "attribute",
      "tableRowAlign": "horizontal",
      "maxLength": 75,
      "preview": false,
      "listable": true,
      "formClass": "Object",
      "hidden": false,
      "link": false,
      "childForm": null,
      "linkAction": "",
      "dayAfter": "",
      "min": 0,
      "transientElement": false,
      "listField": "",
      "attribute": "attribute",
      "cols": 0,
      "value": "",
      "dependantKey": "",
      "key": false,
      "helpText": "",
      "max": 0,
      "seachable": false,
      "parentForm": null,
      "label": "Attribute",
      "rows": 0,
      "yearBefore": "",
      "controlType": "text",
      "displayWidth": "",
      "width": 0,
      "monthAfter": ""
    },
    {
      "listOptions": [],
      "ruleGroups": [],
      "validType": "none",
      "dayBefore": "",
      "defaultValue": "",
      "minLength": 0,
      "tooltip": true,
      "elementsPerColumn": 0,
      "rules": [],
      "formFlowKey": false,
      "required": false,
      "relation": null,
      "monthBefore": "",
      "tab": false,
      "dateBefore": "",
      "folderAutoCreate": false,
      "exclude": false,
      "events": [],
      "placeHolder": "",
      "group": 0,
      "height": 0,
      "thumbnail": false,
      "depends": "",
      "dataType": "",
      "yearAfter": "",
      "format": "",
      "readOnly": "",
      "dataQuery": "",
      "customTemplate": "",
      "regExp": "",
      "accept": "",
      "matchWith": "",
      "dateAfter": "",
      "folder": "0",
      "fileSize": "0",
      "unique": false,
      "mappingField": "",
      "name": "oldValue",
      "tableRowAlign": "horizontal",
      "maxLength": 75,
      "preview": false,
      "listable": true,
      "formClass": "Object",
      "hidden": false,
      "link": false,
      "childForm": null,
      "linkAction": "",
      "dayAfter": "",
      "min": 0,
      "transientElement": false,
      "listField": "",
      "attribute": "oldValue",
      "cols": 0,
      "value": "",
      "dependantKey": "",
      "key": false,
      "helpText": "",
      "max": 0,
      "seachable": false,
      "parentForm": null,
      "label": "Old Value",
      "rows": 0,
      "yearBefore": "",
      "controlType": "text",
      "displayWidth": "",
      "width": 0,
      "monthAfter": ""
    },
    {
      "listOptions": [],
      "ruleGroups": [],
      "validType": "none",
      "dayBefore": "",
      "defaultValue": "",
      "minLength": 0,
      "tooltip": true,
      "elementsPerColumn": 0,
      "rules": [],
      "formFlowKey": false,
      "required": false,
      "relation": null,
      "monthBefore": "",
      "tab": false,
      "dateBefore": "",
      "folderAutoCreate": false,
      "exclude": false,
      "events": [],
      "placeHolder": "",
      "group": 0,
      "height": 0,
      "thumbnail": false,
      "depends": "",
      "dataType": "",
      "yearAfter": "",
      "format": "",
      "readOnly": "",
      "dataQuery": "",
      "customTemplate": "",
      "regExp": "",
      "accept": "",
      "matchWith": "",
      "dateAfter": "",
      "folder": "0",
      "fileSize": "0",
      "unique": false,
      "mappingField": "",
      "name": "newValue",
      "tableRowAlign": "horizontal",
      "maxLength": 75,
      "preview": false,
      "listable": true,
      "formClass": "Object",
      "hidden": false,
      "link": false,
      "childForm": null,
      "linkAction": "",
      "dayAfter": "",
      "min": 0,
      "transientElement": false,
      "listField": "",
      "attribute": "newValue",
      "cols": 0,
      "value": "",
      "dependantKey": "",
      "key": false,
      "helpText": "",
      "max": 0,
      "seachable": false,
      "parentForm": null,
      "label": "New Value",
      "rows": 0,
      "yearBefore": "",
      "controlType": "text",
      "displayWidth": "",
      "width": 0,
      "monthAfter": ""
    },
    {
      "listOptions": [],
      "ruleGroups": [],
      "validType": "none",
      "dayBefore": "",
      "defaultValue": "",
      "minLength": 0,
      "tooltip": false,
      "elementsPerColumn": 0,
      "rules": [],
      "formFlowKey": false,
      "required": false,
      "relation": null,
      "monthBefore": "",
      "tab": false,
      "dateBefore": "",
      "folderAutoCreate": false,
      "exclude": false,
      "events": [],
      "placeHolder": "",
      "group": 0,
      "height": 0,
      "thumbnail": false,
      "depends": "",
      "dataType": "",
      "yearAfter": "",
      "format": "",
      "readOnly": "",
      "dataQuery": "",
      "customTemplate": "",
      "regExp": "",
      "accept": "",
      "matchWith": "",
      "dateAfter": "",
      "folder": "0",
      "fileSize": "0",
      "unique": false,
      "mappingField": "",
      "name": "firedon",
      "tableRowAlign": "horizontal",
      "maxLength": 75,
      "preview": false,
      "listable": true,
      "formClass": "Object",
      "hidden": false,
      "link": false,
      "childForm": null,
      "linkAction": "",
      "dayAfter": "",
      "min": 0,
      "transientElement": false,
      "listField": "",
      "attribute": "firedon",
      "cols": 0,
      "value": "",
      "dependantKey": "",
      "key": false,
      "helpText": "",
      "max": 0,
      "seachable": true,
      "parentForm": null,
      "label": "Firedon",
      "rows": 0,
      "yearBefore": "",
      "controlType": "text",
      "displayWidth": "",
      "width": 0,
      "monthAfter": ""
    }
  ],
  "listOrder": "",
  "associationOneKey": "",
  "actions": [
    {
      "visible": [],
      "controlType": "button",
      "cssClass": null,
      "applyOn": "table",
      "criterias": [],
      "enable": [],
      "name": "add",
      "action": "add",
      "label": "<i class=\"fas fa-plus\"></i>",
      "title": "Add"
    },
    {
      "visible": [],
      "controlType": "button",
      "cssClass": null,
      "applyOn": "row",
      "criterias": [],
      "enable": [],
      "name": "edit",
      "action": "edit",
      "label": "<i class=\"fas fa-edit\"></i>",
      "title": "Edit"
    },
    {
      "visible": [],
      "controlType": "button",
      "cssClass": null,
      "applyOn": "row",
      "criterias": [],
      "enable": [],
      "name": "delete",
      "action": "delete",
      "label": "<i class=\"fas fa-trash\"></i>",
      "title": "Delete"
    },
    {
      "visible": [],
      "controlType": "button",
      "cssClass": "",
      "applyOn": "row",
      "criterias": [],
      "enable": [],
      "name": "retrigger",
      "action": "default",
      "label": "<i class=\"fa fa-repeat\" aria-hidden=\"true\"></i>",
      "title": "Retrigger"
    }
  ],
  "associationEntity": false,
  "entity": null,
  "primaryKey": null
}